python_chatfuel_class/__init__.py
python_chatfuel_class/class_chatfuel.py
python_chatfuel_class-2.1.3.dist-info/METADATA
python_chatfuel_class-2.1.3.dist-info/RECORD
python_chatfuel_class-2.1.3.dist-info/WHEEL
python_chatfuel_class-2.1.3.dist-info/top_level.txt
