Metadata-Version: 2.1
Name: python-chatfuel-class
Version: 2.1.3
Summary: Python Wrapper for JSON API Chatfuel
Home-page: https://github.com/peter-dinh/class-chatfuel-python
Author: Peter Dinh
Author-email: peterdinh018@gmail.com
License: BSD 3-Clause
Keywords: Package for Chatfuel
Platform: UNKNOWN
Classifier: Intended Audience :: Developers
Classifier: Intended Audience :: Information Technology
Classifier: Natural Language :: English
Classifier: Programming Language :: Python
Classifier: Programming Language :: Python :: 2.7
Classifier: Programming Language :: Python :: 3
Classifier: Programming Language :: Python :: 3.4
Classifier: Programming Language :: Python :: 3.5
Classifier: Programming Language :: Python :: 3.6
Classifier: License :: OSI Approved :: BSD License
Classifier: Operating System :: OS Independent
Classifier: Topic :: Software Development :: Libraries :: Python Modules
Requires-Python: >=2.7,!=3.0.*,!=3.1.*,!=3.2.*,!=3.3.*
Requires-Dist: urllib3
